Paperweekly154/README.md
Paperweekly154/__init__.py
Paperweekly154/__main__.py
Paperweekly154/file.epub
Paperweekly154/index.html
Paperweekly154/css/__init__.py
Paperweekly154/css/annotations.css
Paperweekly154/css/main.css
Paperweekly154/css/normalize.css
Paperweekly154/css/popup.css
Paperweekly154/font/__init__.py
Paperweekly154/font/fontello.eot
Paperweekly154/font/fontello.svg
Paperweekly154/font/fontello.ttf
Paperweekly154/font/fontello.woff
Paperweekly154/img/__init__.py
Paperweekly154/img/annotator-glyph-sprite.png
Paperweekly154/img/annotator-icon-sprite.png
Paperweekly154/img/apple-touch-icon.png
Paperweekly154/img/cancelfullscreen.png
Paperweekly154/img/close.png
Paperweekly154/img/fullscreen.png
Paperweekly154/img/loader.gif
Paperweekly154/img/menu-icon.png
Paperweekly154/img/save.png
Paperweekly154/img/saved.png
Paperweekly154/img/settings-s.png
Paperweekly154/img/settings.png
Paperweekly154/img/star.png
Paperweekly154/js/__init__.py
Paperweekly154/js/epub.js
Paperweekly154/js/epub.min.js
Paperweekly154/js/epub.min.map
Paperweekly154/js/hooks.min.js
Paperweekly154/js/hooks.min.map
Paperweekly154/js/reader.js
Paperweekly154/js/reader.js.map
Paperweekly154/js/reader.min.js
Paperweekly154/js/reader.min.map
Paperweekly154/js/hooks/__init__.py
Paperweekly154/js/hooks/extensions/__init__.py
Paperweekly154/js/hooks/extensions/highlight.js
Paperweekly154/js/libs/__init__.py
Paperweekly154/js/libs/jquery.min.js
Paperweekly154/js/libs/localforage.min.js
Paperweekly154/js/libs/screenfull.js
Paperweekly154/js/libs/screenfull.min.js
Paperweekly154/js/libs/zip.min.js
Paperweekly154/js/plugins/__init__.py
Paperweekly154/js/plugins/hypothesis.js
Paperweekly154/js/plugins/search.js
paperweekly_1_54-2024.3.4.0.dist-info/METADATA
paperweekly_1_54-2024.3.4.0.dist-info/WHEEL
paperweekly_1_54-2024.3.4.0.dist-info/entry_points.txt
paperweekly_1_54-2024.3.4.0.dist-info/top_level.txt
paperweekly_1_54-2024.3.4.0.dist-info/RECORD
